{"url":"http:\/\/www.nightlondon.co.uk\/mason-house","sessions":1,"date":"2016-04-23","site":"lon"}
{"url":"http:\/\/www.nightlondon.co.uk\/musical-shows-london-saturday-23-april-2016","sessions":1,"date":"2016-04-23","site":"lon"}
{"url":"http:\/\/www.nightlondon.co.uk\/live-music\/the-misty-moon-film-society-presents-an-evening-with-nicholas-ball-25-june-london","sessions":1,"date":"2016-04-23","site":"lon"}
{"url":"http:\/\/www.nightlondon.co.uk\/live-music\/the-emma-hamilton-band-23-april-london","sessions":1,"date":"2016-04-23","site":"lon"}
{"url":"http:\/\/www.nightlondon.co.uk\/live-music\/hollywood-undead-20-april-london","sessions":1,"date":"2016-04-23","site":"lon"}
{"url":"http:\/\/www.nightlondon.co.uk\/parties-deep-house-london","sessions":1,"date":"2016-04-23","site":"lon"}
{"url":"http:\/\/www.nightlondon.co.uk\/party\/st-george-s-day-with-edl-23-april-london","sessions":1,"date":"2016-04-23","site":"lon"}
{"url":"http:\/\/www.nightlondon.co.uk\/tickets-london-friday-29-april-2016","sessions":1,"date":"2016-04-23","site":"lon"}
{"url":"http:\/\/www.nightlondon.co.uk\/wembley-arena","sessions":1,"date":"2016-04-23","site":"lon"}
{"url":"http:\/\/www.nightlondon.co.uk\/theatre\/cecilia-lisa-eliceche-cecilia-lisa-eliceche-unison-sadler-s-wells-london","sessions":1,"date":"2016-04-23","site":"lon"}
{"url":"http:\/\/www.nightlondon.co.uk\/the-o2-arena","sessions":1,"date":"2016-04-23","site":"lon"}
{"url":"http:\/\/www.nightlondon.co.uk\/party\/torture-garden-25th-anniversary-23-april-london","sessions":1,"date":"2016-04-23","site":"lon"}
{"url":"http:\/\/www.nightlondon.co.uk\/live-music\/chelsea-40th-birthday-party-the-members-bermondsey-joyriders-23-april-london","sessions":1,"date":"2016-04-23","site":"lon"}
{"url":"http:\/\/www.nightlondon.co.uk\/live-music-neo-folk-london","sessions":1,"date":"2016-04-23","site":"lon"}
{"url":"http:\/\/www.nightlondon.co.uk\/events-breakcore-london","sessions":1,"date":"2016-04-23","site":"lon"}
{"url":"http:\/\/www.nightlondon.co.uk\/electric-brixton","sessions":1,"date":"2016-04-23","site":"lon"}
{"url":"http:\/\/www.nightlondon.co.uk\/chingford-assembly-hall","sessions":1,"date":"2016-04-23","site":"lon"}
{"url":"http:\/\/www.nightlondon.co.uk\/barfly","sessions":1,"date":"2016-04-23","site":"lon"}
{"url":"http:\/\/www.nightlondon.co.uk\/gigs-bluegrass-london","sessions":1,"date":"2016-04-23","site":"lon"}
{"url":"http:\/\/www.nightlondon.co.uk\/events-brit-pop-london","sessions":1,"date":"2016-04-23","site":"lon"}
{"url":"http:\/\/www.nightlondon.co.uk\/kurdish-community-centre","sessions":1,"date":"2016-04-23","site":"lon"}
{"url":"http:\/\/www.nightlondon.co.uk\/gigs-rockabilly-london","sessions":1,"date":"2016-04-23","site":"lon"}
{"url":"http:\/\/www.nightlondon.co.uk\/going-out-london-saturday-23-april-2016","sessions":1,"date":"2016-04-23","site":"lon"}
{"url":"http:\/\/www.nightlondon.co.uk\/gigs-psychedelic-rock-london","sessions":1,"date":"2016-04-23","site":"lon"}
{"url":"http:\/\/www.nightlondon.co.uk\/jamboree","sessions":2,"date":"2016-04-23","site":"lon"}
{"url":"http:\/\/www.nightlondon.co.uk\/live-music\/rockfeedback-presents-sophia-9-may-london","sessions":2,"date":"2016-04-23","site":"lon"}
{"url":"http:\/\/www.nightlondon.co.uk\/events-grime-london","sessions":4,"date":"2016-04-23","site":"lon"}
