{"url":"http:\/\/www.nightlondon.co.uk\/party\/anthem-11-november-london","sessions":1,"date":"2016-11-10","site":"lon"}
{"url":"http:\/\/www.nightlondon.co.uk\/magic-shows-london-wednesday-16-november-2016","sessions":1,"date":"2016-11-10","site":"lon"}
{"url":"http:\/\/www.nightlondon.co.uk\/party\/club-the-mammoth-presents-psychic-tv-7-november-london","sessions":1,"date":"2016-11-10","site":"lon"}
{"url":"http:\/\/www.nightlondon.co.uk\/party\/friday-at-toy-room-11-november-london","sessions":1,"date":"2016-11-10","site":"lon"}
{"url":"http:\/\/www.nightlondon.co.uk\/party\/innervisions-dixon-b2b-ame-13-november-london","sessions":1,"date":"2016-11-10","site":"lon"}
{"url":"http:\/\/www.nightlondon.co.uk\/live-music\/union-chapel-singers-21-november-london","sessions":1,"date":"2016-11-10","site":"lon"}
{"url":"http:\/\/www.nightlondon.co.uk\/live-music\/the-ukulele-orchestra-of-great-britain-26-november-london","sessions":1,"date":"2016-11-10","site":"lon"}
{"url":"http:\/\/www.nightlondon.co.uk\/live-music\/oval-space-cinema-x-songkick-presents-stop-making-sense-10-november-london","sessions":1,"date":"2016-11-10","site":"lon"}
{"url":"http:\/\/www.nightlondon.co.uk\/live-music\/sound-salute-2016-25-november-london","sessions":1,"date":"2016-11-10","site":"lon"}
{"url":"http:\/\/www.nightlondon.co.uk\/live-music\/sugar-daddy-spirit-revolution-band-17-november-london","sessions":1,"date":"2016-11-10","site":"lon"}
{"url":"http:\/\/www.nightlondon.co.uk\/live-music\/sunday-buzz-allan-harris-13-november-london","sessions":1,"date":"2016-11-10","site":"lon"}
{"url":"http:\/\/www.nightlondon.co.uk\/party\/new-business-with-paramida-and-dj-sonikku-3-december-london","sessions":1,"date":"2016-11-10","site":"lon"}
{"url":"http:\/\/www.nightlondon.co.uk\/party\/the-camden-rocks-indie-rock-all-dayer-19-november-london","sessions":1,"date":"2016-11-10","site":"lon"}
{"url":"http:\/\/www.nightlondon.co.uk\/theatre\/sidi-larbi-cherkaoui-m-longa-sadler-s-wells-london","sessions":1,"date":"2016-11-10","site":"lon"}
{"url":"http:\/\/www.nightlondon.co.uk\/theatre\/simon-slack-the-fantasist-soho-theatre-london","sessions":1,"date":"2016-11-10","site":"lon"}
{"url":"http:\/\/www.nightlondon.co.uk\/theatre\/the-pod-of-maximum-damage-featuring-adam-riches-jessica-ransom-nick-mohammed-14-december-london","sessions":1,"date":"2016-11-10","site":"lon"}
{"url":"http:\/\/www.nightlondon.co.uk\/wyndham-s-theatre","sessions":1,"date":"2016-11-10","site":"lon"}
{"url":"http:\/\/www.nightlondon.co.uk\/theatre\/shaun-kitchener-s-six-pack-leicester-square-theatre-london","sessions":1,"date":"2016-11-10","site":"lon"}
{"url":"http:\/\/www.nightlondon.co.uk\/theatre\/new-english-ballet-theatre-quint-essential-peacock-theatre-london","sessions":1,"date":"2016-11-10","site":"lon"}
{"url":"http:\/\/www.nightlondon.co.uk\/theatre-tickets-camden-centre-november-2016","sessions":1,"date":"2016-11-10","site":"lon"}
{"url":"http:\/\/www.nightlondon.co.uk\/theatre-tickets-kings-place-january-2017","sessions":1,"date":"2016-11-10","site":"lon"}
{"url":"http:\/\/www.nightlondon.co.uk\/theatre\/classical-spectacular-royal-albert-hall-london","sessions":1,"date":"2016-11-10","site":"lon"}
{"url":"http:\/\/www.nightlondon.co.uk\/theatre\/keith-johnstone-s-maestro-impro-13-november-london","sessions":1,"date":"2016-11-10","site":"lon"}
{"url":"http:\/\/www.nightlondon.co.uk\/live-music\/miles-from-kinshasa-ray-blk-the-age-of-l-u-n-a-22-november-london","sessions":1,"date":"2016-11-10","site":"lon"}
{"url":"http:\/\/www.nightlondon.co.uk\/live-music\/mama-dakas-false-idols-deep-city-diver-13-october-london","sessions":1,"date":"2016-11-10","site":"lon"}
{"url":"http:\/\/www.nightlondon.co.uk\/gigs-grime-london","sessions":1,"date":"2016-11-10","site":"lon"}
{"url":"http:\/\/www.nightlondon.co.uk\/going-out-london-thursday-10-november-2016","sessions":1,"date":"2016-11-10","site":"lon"}
{"url":"http:\/\/www.nightlondon.co.uk\/live-music-bluegrass-london","sessions":1,"date":"2016-11-10","site":"lon"}
{"url":"http:\/\/www.nightlondon.co.uk\/live-music-london-saturday-14-january-2017","sessions":1,"date":"2016-11-10","site":"lon"}
{"url":"http:\/\/www.nightlondon.co.uk\/events-royal-albert-hall-september-2017","sessions":1,"date":"2016-11-10","site":"lon"}
{"url":"http:\/\/www.nightlondon.co.uk\/events-bossa-nova-london","sessions":1,"date":"2016-11-10","site":"lon"}
{"url":"http:\/\/www.nightlondon.co.uk\/","sessions":1,"date":"2016-11-10","site":"lon"}
{"url":"http:\/\/www.nightlondon.co.uk\/clubbing-thanksgiving-day-london","sessions":1,"date":"2016-11-10","site":"lon"}
{"url":"http:\/\/www.nightlondon.co.uk\/concerts-hardcore-london","sessions":1,"date":"2016-11-10","site":"lon"}
{"url":"http:\/\/www.nightlondon.co.uk\/live-music\/armaan-malik-on-the-official-ticketmaster-marketplace-24-september-london","sessions":1,"date":"2016-11-10","site":"lon"}
{"url":"http:\/\/www.nightlondon.co.uk\/live-music\/acid-arab-3-november-london","sessions":1,"date":"2016-11-10","site":"lon"}
{"url":"http:\/\/www.nightlondon.co.uk\/live-music\/jake-bugg-4-december-london","sessions":1,"date":"2016-11-10","site":"lon"}
{"url":"http:\/\/www.nightlondon.co.uk\/live-music\/law-rocks-10-november-london","sessions":1,"date":"2016-11-10","site":"lon"}
{"url":"http:\/\/www.nightlondon.co.uk\/live-music\/live-molotov-jukebox-2-december-london","sessions":1,"date":"2016-11-10","site":"lon"}
{"url":"http:\/\/www.nightlondon.co.uk\/live-music\/gryphon-16-september-london","sessions":1,"date":"2016-11-10","site":"lon"}
{"url":"http:\/\/www.nightlondon.co.uk\/live-music\/goran-bregovic-bijelo-dugme-23-february-london","sessions":1,"date":"2016-11-10","site":"lon"}
{"url":"http:\/\/www.nightlondon.co.uk\/live-music\/back-of-the-head-with-a-brick-sean-mahoney-dairus-mcfarlane-10-november-london","sessions":1,"date":"2016-11-10","site":"lon"}
{"url":"http:\/\/www.nightlondon.co.uk\/live-music\/curtis-stigers-4-december-london","sessions":1,"date":"2016-11-10","site":"lon"}
{"url":"http:\/\/www.nightlondon.co.uk\/live-music\/christmas-cabaret-lunch-ronnie-scott-s-london","sessions":1,"date":"2016-11-10","site":"lon"}
{"url":"http:\/\/www.nightlondon.co.uk\/live-music\/david-torn-sun-of-goldfinger-w-tim-berne-ches-smith-22-january-london","sessions":1,"date":"2016-11-10","site":"lon"}
{"url":"http:\/\/www.nightlondon.co.uk\/gigs-bluegrass-london","sessions":2,"date":"2016-11-10","site":"lon"}
{"url":"http:\/\/www.nightlondon.co.uk\/live-music\/attack-on-mars-angelo-tristan-band-flawless-carbon-10-november-london","sessions":3,"date":"2016-11-10","site":"lon"}
{"url":"http:\/\/www.nightlondon.co.uk\/events-grime-london","sessions":4,"date":"2016-11-10","site":"lon"}
