{"url":"http:\/\/www.nightlondon.co.uk\/live-music\/poetry-brothel-london-lorca-and-the-duende-of-flamenco-1-october-london","sessions":1,"date":"2016-10-02","site":"lon"}
{"url":"http:\/\/www.nightlondon.co.uk\/live-music\/sarah-jane-morris-antonio-forcione-quintet-ronnie-scott-s-london","sessions":1,"date":"2016-10-02","site":"lon"}
{"url":"http:\/\/www.nightlondon.co.uk\/live-music\/mick-jenkins-26-october-london","sessions":1,"date":"2016-10-02","site":"lon"}
{"url":"http:\/\/www.nightlondon.co.uk\/live-music\/lost-in-the-manor-presents-flight-brigade-farrago-27-october-london","sessions":1,"date":"2016-10-02","site":"lon"}
{"url":"http:\/\/www.nightlondon.co.uk\/live-music\/kraak-presents-spencer-clark-sea-urchin-5-october-london","sessions":1,"date":"2016-10-02","site":"lon"}
{"url":"http:\/\/www.nightlondon.co.uk\/live-music\/liam-noble-mark-lewandowski-paul-clarvis-play-fats-waller-bureau-of-atomic-tourism-14-november-london","sessions":1,"date":"2016-10-02","site":"lon"}
{"url":"http:\/\/www.nightlondon.co.uk\/live-music\/sunday-live-music-sessions-the-fallen-heroes-2-october-london","sessions":1,"date":"2016-10-02","site":"lon"}
{"url":"http:\/\/www.nightlondon.co.uk\/party\/bashment-chill-30-september-london","sessions":1,"date":"2016-10-02","site":"lon"}
{"url":"http:\/\/www.nightlondon.co.uk\/theatre\/tongue-fu-8-december-london","sessions":1,"date":"2016-10-02","site":"lon"}
{"url":"http:\/\/www.nightlondon.co.uk\/whats-on-london-october-2016","sessions":1,"date":"2016-10-02","site":"lon"}
{"url":"http:\/\/www.nightlondon.co.uk\/theatre\/richard-gadd-monkey-see-monkey-do-soho-theatre-live-15-october-london","sessions":1,"date":"2016-10-02","site":"lon"}
{"url":"http:\/\/www.nightlondon.co.uk\/the-100-club","sessions":1,"date":"2016-10-02","site":"lon"}
{"url":"http:\/\/www.nightlondon.co.uk\/party\/cafe-mambo-ibiza-london-closing-party-8-october-london","sessions":1,"date":"2016-10-02","site":"lon"}
{"url":"http:\/\/www.nightlondon.co.uk\/party\/celebrity-saturday-s-at-cafe-de-paris-1-october-london","sessions":1,"date":"2016-10-02","site":"lon"}
{"url":"http:\/\/www.nightlondon.co.uk\/live-music\/f3ast-fest-2016-toulouse-lautrec-firma-implant-pentru-refuz-luna-amara-15-october-london","sessions":1,"date":"2016-10-02","site":"lon"}
{"url":"http:\/\/www.nightlondon.co.uk\/live-music\/drumcode-halloween-29-october-london","sessions":1,"date":"2016-10-02","site":"lon"}
{"url":"http:\/\/www.nightlondon.co.uk\/gigs-ambient-london","sessions":1,"date":"2016-10-02","site":"lon"}
{"url":"http:\/\/www.nightlondon.co.uk\/electric-brixton","sessions":1,"date":"2016-10-02","site":"lon"}
{"url":"http:\/\/www.nightlondon.co.uk\/chingford-assembly-hall","sessions":1,"date":"2016-10-02","site":"lon"}
{"url":"http:\/\/www.nightlondon.co.uk\/bush-hall","sessions":1,"date":"2016-10-02","site":"lon"}
{"url":"http:\/\/www.nightlondon.co.uk\/gigs-bluegrass-london","sessions":1,"date":"2016-10-02","site":"lon"}
{"url":"http:\/\/www.nightlondon.co.uk\/events-bossa-nova-london","sessions":1,"date":"2016-10-02","site":"lon"}
{"url":"http:\/\/www.nightlondon.co.uk\/gigs-rockabilly-london","sessions":1,"date":"2016-10-02","site":"lon"}
{"url":"http:\/\/www.nightlondon.co.uk\/live-music\/aka-comedy-club-with-marcel-lucont-the-islington-london-22-november-london","sessions":1,"date":"2016-10-02","site":"lon"}
{"url":"http:\/\/www.nightlondon.co.uk\/live-music\/chris-holmes-overworld-silk-road-the-end-of-grace-1-october-london","sessions":1,"date":"2016-10-02","site":"lon"}
{"url":"http:\/\/www.nightlondon.co.uk\/live-music-rumba-london","sessions":1,"date":"2016-10-02","site":"lon"}
{"url":"http:\/\/www.nightlondon.co.uk\/live-music-london-saturday-15-october-2016","sessions":2,"date":"2016-10-02","site":"lon"}
{"url":"http:\/\/www.nightlondon.co.uk\/live-music\/brandee-younger-tribute-to-alice-coltrane-dorothy-ashby-10-november-london","sessions":2,"date":"2016-10-02","site":"lon"}
{"url":"http:\/\/www.nightlondon.co.uk\/party\/battle-of-the-unis-4-october-london","sessions":2,"date":"2016-10-02","site":"lon"}
{"url":"http:\/\/www.nightlondon.co.uk\/live-music\/mixer-hit-festival-22-october-london","sessions":3,"date":"2016-10-02","site":"lon"}
{"url":"http:\/\/www.nightlondon.co.uk\/events-grime-london","sessions":8,"date":"2016-10-02","site":"lon"}
