{"url":"http:\/\/www.nightlondon.co.uk\/live-music\/josephine-foster-solo-satoshi-yamada-25-february-london","sessions":1,"date":"2016-02-27","site":"lon"}
{"url":"http:\/\/www.nightlondon.co.uk\/live-music\/louis-berry-19-may-london","sessions":1,"date":"2016-02-27","site":"lon"}
{"url":"http:\/\/www.nightlondon.co.uk\/live-music\/paddy-casey-the-islington-london-27-february-london","sessions":1,"date":"2016-02-27","site":"lon"}
{"url":"http:\/\/www.nightlondon.co.uk\/live-music\/friday-night-is-music-night-fabulous-films-of-the-fifties-24-february-london","sessions":1,"date":"2016-02-27","site":"lon"}
{"url":"http:\/\/www.nightlondon.co.uk\/live-music\/cat-bones-and-candles-8-march-london","sessions":1,"date":"2016-02-27","site":"lon"}
{"url":"http:\/\/www.nightlondon.co.uk\/live-music\/atlantic-soul-orchestra-5-march-london","sessions":1,"date":"2016-02-27","site":"lon"}
{"url":"http:\/\/www.nightlondon.co.uk\/live-music\/carnalondres-2016-if-avioes-do-forro-28-february-london","sessions":1,"date":"2016-02-27","site":"lon"}
{"url":"http:\/\/www.nightlondon.co.uk\/live-music\/part-chimp-fiend-hag-support-27-february-london","sessions":1,"date":"2016-02-27","site":"lon"}
{"url":"http:\/\/www.nightlondon.co.uk\/live-music\/seven-sins-friday-11-march-london","sessions":1,"date":"2016-02-27","site":"lon"}
{"url":"http:\/\/www.nightlondon.co.uk\/things-to-do-tonight-london","sessions":1,"date":"2016-02-27","site":"lon"}
{"url":"http:\/\/www.nightlondon.co.uk\/wembley-arena","sessions":1,"date":"2016-02-27","site":"lon"}
{"url":"http:\/\/www.nightlondon.co.uk\/theatre\/laugh-hard-an-alan-rickman-comedy-tribute-evening-28-february-london","sessions":1,"date":"2016-02-27","site":"lon"}
{"url":"http:\/\/www.nightlondon.co.uk\/party\/duckie-27-february-london","sessions":1,"date":"2016-02-27","site":"lon"}
{"url":"http:\/\/www.nightlondon.co.uk\/main\/type:Going Out.day:Saturday 30 July 2016\/30","sessions":1,"date":"2016-02-27","site":"lon"}
{"url":"http:\/\/www.nightlondon.co.uk\/party\/cargo-presents-quartz-26-february-london","sessions":1,"date":"2016-02-27","site":"lon"}
{"url":"http:\/\/www.nightlondon.co.uk\/live-music\/al-di-meola-elysium-more-ronnie-scott-s-london","sessions":1,"date":"2016-02-27","site":"lon"}
{"url":"http:\/\/www.nightlondon.co.uk\/live-music-mod-london","sessions":1,"date":"2016-02-27","site":"lon"}
{"url":"http:\/\/www.nightlondon.co.uk\/events-deep-house-london","sessions":1,"date":"2016-02-27","site":"lon"}
{"url":"http:\/\/www.nightlondon.co.uk\/concerts-post-punk-london","sessions":1,"date":"2016-02-27","site":"lon"}
{"url":"http:\/\/www.nightlondon.co.uk\/comedy-london-saturday-30-july-2016","sessions":1,"date":"2016-02-27","site":"lon"}
{"url":"http:\/\/www.nightlondon.co.uk\/","sessions":1,"date":"2016-02-27","site":"lon"}
{"url":"http:\/\/www.nightlondon.co.uk\/gig-guide-london-february-2016","sessions":1,"date":"2016-02-27","site":"lon"}
{"url":"http:\/\/www.nightlondon.co.uk\/events-acid-house-london","sessions":1,"date":"2016-02-27","site":"lon"}
{"url":"http:\/\/www.nightlondon.co.uk\/gigs-psychedelic-rock-london","sessions":1,"date":"2016-02-27","site":"lon"}
{"url":"http:\/\/www.nightlondon.co.uk\/gigs-rockabilly-london","sessions":1,"date":"2016-02-27","site":"lon"}
{"url":"http:\/\/www.nightlondon.co.uk\/live-bands-bossa-nova-london","sessions":1,"date":"2016-02-27","site":"lon"}
{"url":"http:\/\/www.nightlondon.co.uk\/gigs-rnb-london","sessions":1,"date":"2016-02-27","site":"lon"}
{"url":"http:\/\/www.nightlondon.co.uk\/gigs-london-march-2016","sessions":2,"date":"2016-02-27","site":"lon"}
{"url":"http:\/\/www.nightlondon.co.uk\/events-bossa-nova-london","sessions":2,"date":"2016-02-27","site":"lon"}
{"url":"http:\/\/www.nightlondon.co.uk\/novello-theatre","sessions":2,"date":"2016-02-27","site":"lon"}
{"url":"http:\/\/www.nightlondon.co.uk\/whats-on-tonight-london","sessions":2,"date":"2016-02-27","site":"lon"}
{"url":"http:\/\/www.nightlondon.co.uk\/events-lovers-rock-london","sessions":3,"date":"2016-02-27","site":"lon"}
{"url":"http:\/\/www.nightlondon.co.uk\/events-grime-london","sessions":4,"date":"2016-02-27","site":"lon"}
