{"url":"http:\/\/www.nightlondon.co.uk\/party\/the-gallery-third-party-presents-release-records-3-november-london","sessions":1,"date":"2017-10-16","site":"lon"}
{"url":"http:\/\/www.nightlondon.co.uk\/main\/type:Going Out.day:Monday 26 February 2018\/20","sessions":1,"date":"2017-10-16","site":"lon"}
{"url":"http:\/\/www.nightlondon.co.uk\/live-music\/valerie-tryon-recital-15-october-london","sessions":1,"date":"2017-10-16","site":"lon"}
{"url":"http:\/\/www.nightlondon.co.uk\/theatre-london-october-2017","sessions":1,"date":"2017-10-16","site":"lon"}
{"url":"http:\/\/www.nightlondon.co.uk\/theatre\/project-new-sun-sinosynthesis-22-october-london","sessions":1,"date":"2017-10-16","site":"lon"}
{"url":"http:\/\/www.nightlondon.co.uk\/theatre\/wegottickets-mca-heat-2-with-tina-t-urner-tea-lady-20-january-london","sessions":1,"date":"2017-10-16","site":"lon"}
{"url":"http:\/\/www.nightlondon.co.uk\/theatre\/roy-budd-s-the-phantom-of-the-opera-8-october-london","sessions":1,"date":"2017-10-16","site":"lon"}
{"url":"http:\/\/www.nightlondon.co.uk\/live-music\/up-tight-16-november-london","sessions":1,"date":"2017-10-16","site":"lon"}
{"url":"http:\/\/www.nightlondon.co.uk\/live-music\/the-thing-lume-meets-werkstatt-berne-19-november-london","sessions":1,"date":"2017-10-16","site":"lon"}
{"url":"http:\/\/www.nightlondon.co.uk\/live-music-bossa-nova-london","sessions":1,"date":"2017-10-16","site":"lon"}
{"url":"http:\/\/www.nightlondon.co.uk\/live-music-bluegrass-london","sessions":1,"date":"2017-10-16","site":"lon"}
{"url":"http:\/\/www.nightlondon.co.uk\/live-music-ambient-london","sessions":1,"date":"2017-10-16","site":"lon"}
{"url":"http:\/\/www.nightlondon.co.uk\/live-music-london-october-2017","sessions":1,"date":"2017-10-16","site":"lon"}
{"url":"http:\/\/www.nightlondon.co.uk\/live-music\/all-the-wild-folk-with-the-drystones-sam-walter-14-october-london","sessions":1,"date":"2017-10-16","site":"lon"}
{"url":"http:\/\/www.nightlondon.co.uk\/live-music\/helloween-pumpkins-united-14-november-london","sessions":1,"date":"2017-10-16","site":"lon"}
{"url":"http:\/\/www.nightlondon.co.uk\/live-music\/annie-mac-presents-amp-collected-19-october-london","sessions":1,"date":"2017-10-16","site":"lon"}
{"url":"http:\/\/www.nightlondon.co.uk\/en\/o2-shepherds-bush-empire","sessions":1,"date":"2017-10-16","site":"lon"}
