{"url":"http:\/\/www.nightlondon.co.uk\/party\/polo-the-cuban-brothers-4-february-london","sessions":1,"date":"2017-01-20","site":"lon"}
{"url":"http:\/\/www.nightlondon.co.uk\/party\/friday-at-libertine-20-january-london","sessions":1,"date":"2017-01-20","site":"lon"}
{"url":"http:\/\/www.nightlondon.co.uk\/party\/saturday-at-libertine-21-january-london","sessions":1,"date":"2017-01-20","site":"lon"}
{"url":"http:\/\/www.nightlondon.co.uk\/theatre\/abandoman-life-rhymes-soho-theatre-london","sessions":1,"date":"2017-01-20","site":"lon"}
{"url":"http:\/\/www.nightlondon.co.uk\/theatre\/jerry-sadowitz-magic-challenge-soho-theatre-london","sessions":1,"date":"2017-01-20","site":"lon"}
{"url":"http:\/\/www.nightlondon.co.uk\/party\/acrylic-london-sir-spyro-w-ygg-amy-becker-iglooghost-dinamarca-mungo-3-february-london","sessions":1,"date":"2017-01-20","site":"lon"}
{"url":"http:\/\/www.nightlondon.co.uk\/live-music\/lea-lea-die-pretty-vol-ii-ep-launch-avante-black-oh-annie-oh-dj-set-2-march-london","sessions":1,"date":"2017-01-20","site":"lon"}
{"url":"http:\/\/www.nightlondon.co.uk\/events-le-quecumbar-january-2017","sessions":1,"date":"2017-01-20","site":"lon"}
{"url":"http:\/\/www.nightlondon.co.uk\/gigs-math-rock-london","sessions":1,"date":"2017-01-20","site":"lon"}
{"url":"http:\/\/www.nightlondon.co.uk\/live-music-rocksteady-london","sessions":1,"date":"2017-01-20","site":"lon"}
{"url":"http:\/\/www.nightlondon.co.uk\/live-music\/jazz2rocksteady-14-january-london","sessions":1,"date":"2017-01-20","site":"lon"}
{"url":"http:\/\/www.nightlondon.co.uk\/gig-guide-the-good-ship-january-2017","sessions":2,"date":"2017-01-20","site":"lon"}
