{"url":"http:\/\/www.nightnyc.net\/mcginn-cazale-theatre","sessions":1,"date":"2016-10-12","site":"nyc"}
{"url":"http:\/\/www.nightnyc.net\/main\/type:Live Music.city:New York\/10","sessions":1,"date":"2016-10-12","site":"nyc"}
{"url":"http:\/\/www.nightnyc.net\/live-music\/three-centuries-of-swedish-music-per-tengstrand-piano-16-march-new-york","sessions":1,"date":"2016-10-12","site":"nyc"}
{"url":"http:\/\/www.nightnyc.net\/obras-teatro-new-york-febrero-2017","sessions":1,"date":"2016-10-12","site":"nyc"}
{"url":"http:\/\/www.nightnyc.net\/sob-s","sessions":1,"date":"2016-10-12","site":"nyc"}
{"url":"http:\/\/www.nightnyc.net\/tickets-tonight-new-york","sessions":1,"date":"2016-10-12","site":"nyc"}
{"url":"http:\/\/www.nightnyc.net\/theatre\/ralphie-may-4-november-new-york","sessions":1,"date":"2016-10-12","site":"nyc"}
{"url":"http:\/\/www.nightnyc.net\/teatro\/the-gabriels-election-year-in-the-life-of-one-family-play-three-women-of-a-certain-age-public-theater-new-york","sessions":1,"date":"2016-10-12","site":"nyc"}
{"url":"http:\/\/www.nightnyc.net\/live-music\/marty-allen-karon-kate-blackwell-20-october-new-york","sessions":1,"date":"2016-10-12","site":"nyc"}
{"url":"http:\/\/www.nightnyc.net\/live-music\/johnny-o-neal-60th-birthday-celebration-dizzy-s-new-york","sessions":1,"date":"2016-10-12","site":"nyc"}
{"url":"http:\/\/www.nightnyc.net\/joe-s-pub","sessions":1,"date":"2016-10-12","site":"nyc"}
{"url":"http:\/\/www.nightnyc.net\/fiestas-new-york","sessions":1,"date":"2016-10-12","site":"nyc"}
{"url":"http:\/\/www.nightnyc.net\/conciertos-salsa-new-york","sessions":1,"date":"2016-10-12","site":"nyc"}
{"url":"http:\/\/www.nightnyc.net\/le-poisson-rouge","sessions":1,"date":"2016-10-12","site":"nyc"}
{"url":"http:\/\/www.nightnyc.net\/live-music-tonight-new-york","sessions":1,"date":"2016-10-12","site":"nyc"}
{"url":"http:\/\/www.nightnyc.net\/live-music\/jk-kim-dong-uk-and-so-hyang-joint-concert-in-new-york-2016-16-september-greenvale","sessions":1,"date":"2016-10-12","site":"nyc"}
{"url":"http:\/\/www.nightnyc.net\/live-music\/antonis-remos-28-october-new-york","sessions":1,"date":"2016-10-12","site":"nyc"}
{"url":"http:\/\/www.nightnyc.net\/calendario-conciertos-newark-diciembre-2016","sessions":1,"date":"2016-10-12","site":"nyc"}
