{"url":"http:\/\/www.nightnyc.net\/main\/type:Live Music.city:New York.ymonth:June 2016\/30","sessions":1,"date":"2016-06-15","site":"nyc"}
{"url":"http:\/\/www.nightnyc.net\/live-music\/that-s-right-on-the-sun-shapes-on-tape-alex-rubin-3-july-new-york","sessions":1,"date":"2016-06-15","site":"nyc"}
{"url":"http:\/\/www.nightnyc.net\/live-music\/marilyn-maye-13-january-new-york","sessions":1,"date":"2016-06-15","site":"nyc"}
{"url":"http:\/\/www.nightnyc.net\/main\/type:Live Music.music:Jazz.city:New York\/30","sessions":1,"date":"2016-06-15","site":"nyc"}
{"url":"http:\/\/www.nightnyc.net\/obras-teatro-lincoln-center","sessions":1,"date":"2016-06-15","site":"nyc"}
{"url":"http:\/\/www.nightnyc.net\/teatro-new-york","sessions":1,"date":"2016-06-15","site":"nyc"}
{"url":"http:\/\/www.nightnyc.net\/sanders-studio","sessions":1,"date":"2016-06-15","site":"nyc"}
{"url":"http:\/\/www.nightnyc.net\/party\/skyroom-saturdays-everyone-free-u0026-more-on-cris-a-c-list-25-june-new-york","sessions":1,"date":"2016-06-15","site":"nyc"}
{"url":"http:\/\/www.nightnyc.net\/live-music\/alex-leonard-15-june-new-york","sessions":1,"date":"2016-06-15","site":"nyc"}
{"url":"http:\/\/www.nightnyc.net\/live-music-new-york-june-2016","sessions":1,"date":"2016-06-15","site":"nyc"}
{"url":"http:\/\/www.nightnyc.net\/conciertos-hardcore-new-york","sessions":1,"date":"2016-06-15","site":"nyc"}
{"url":"http:\/\/www.nightnyc.net\/concierto\/brian-newman-presents-eyes-on-the-city-an-album-preview-25-27-junio-new-york","sessions":1,"date":"2016-06-15","site":"nyc"}
{"url":"http:\/\/www.nightnyc.net\/calendario-conciertos-blues-new-york","sessions":1,"date":"2016-06-15","site":"nyc"}
{"url":"http:\/\/www.nightnyc.net\/eventos-deep-house-new-york","sessions":1,"date":"2016-06-15","site":"nyc"}
{"url":"http:\/\/www.nightnyc.net\/fiesta\/bathhouse-2nd-annual-pride-event-24-junio-new-york","sessions":1,"date":"2016-06-15","site":"nyc"}
{"url":"http:\/\/www.nightnyc.net\/joe-s-pub","sessions":1,"date":"2016-06-15","site":"nyc"}
{"url":"http:\/\/www.nightnyc.net\/guia-conciertos-new-york-febrero-2017","sessions":1,"date":"2016-06-15","site":"nyc"}
{"url":"http:\/\/www.nightnyc.net\/fiestas-underground-new-york","sessions":1,"date":"2016-06-15","site":"nyc"}
{"url":"http:\/\/www.nightnyc.net\/events-reggae-new-york","sessions":2,"date":"2016-06-15","site":"nyc"}
