{"url":"http:\/\/www.nightnyc.net\/live-music\/ecuador-nights-with-daniel-heredia-y-su-banda-featuring-multikulti-14-july-new-york","sessions":1,"date":"2016-07-14","site":"nyc"}
{"url":"http:\/\/www.nightnyc.net\/live-music\/buckethead-23-september-new-york","sessions":1,"date":"2016-07-14","site":"nyc"}
{"url":"http:\/\/www.nightnyc.net\/live-music\/6th-annual-christmas-in-new-york-with-denver-and-the-mile-high-orchestra-travis-cottrell-marcia-ware-and-the-american-festival-choir-21-november-new-york","sessions":1,"date":"2016-07-14","site":"nyc"}
{"url":"http:\/\/www.nightnyc.net\/live-music\/54-sings-hair-54-below-new-york","sessions":1,"date":"2016-07-14","site":"nyc"}
{"url":"http:\/\/www.nightnyc.net\/live-music\/imafuji-kai-japanese-traditional-music-ensemble-19-september-new-york","sessions":1,"date":"2016-07-14","site":"nyc"}
{"url":"http:\/\/www.nightnyc.net\/musica-directo-newark-domingo-21-agosto-2016","sessions":1,"date":"2016-07-14","site":"nyc"}
{"url":"http:\/\/www.nightnyc.net\/theatre\/allan-finn-14-july-new-york","sessions":1,"date":"2016-07-14","site":"nyc"}
{"url":"http:\/\/www.nightnyc.net\/teatro\/til-death-do-us-fart-pop-roulette-s-amazing-earth-21-julio-new-york","sessions":1,"date":"2016-07-14","site":"nyc"}
{"url":"http:\/\/www.nightnyc.net\/programacion-radio-city-hall","sessions":1,"date":"2016-07-14","site":"nyc"}
{"url":"http:\/\/www.nightnyc.net\/live-music-tonight-new-york","sessions":1,"date":"2016-07-14","site":"nyc"}
{"url":"http:\/\/www.nightnyc.net\/live-music-bossa-nova-new-york","sessions":1,"date":"2016-07-14","site":"nyc"}
{"url":"http:\/\/www.nightnyc.net\/concierto\/garth-brooks-trisha-yearwood-yankee-stadium-new-york","sessions":1,"date":"2016-07-14","site":"nyc"}
{"url":"http:\/\/www.nightnyc.net\/concierto\/craig-greenberg-12-agosto-new-york","sessions":1,"date":"2016-07-14","site":"nyc"}
{"url":"http:\/\/www.nightnyc.net\/concierto\/orrin-evans-presents-philly-meets-new-york-smoke-jazz-new-york","sessions":1,"date":"2016-07-14","site":"nyc"}
{"url":"http:\/\/www.nightnyc.net\/conciertos-new-york-enero-2017","sessions":1,"date":"2016-07-14","site":"nyc"}
{"url":"http:\/\/www.nightnyc.net\/live-gigs-new-york-october-2016","sessions":1,"date":"2016-07-14","site":"nyc"}
{"url":"http:\/\/www.nightnyc.net\/events-reggae-new-york","sessions":1,"date":"2016-07-14","site":"nyc"}
{"url":"http:\/\/www.nightnyc.net\/conciertos-salsa-new-york","sessions":1,"date":"2016-07-14","site":"nyc"}
{"url":"http:\/\/www.nightnyc.net\/live-music\/earl-klugh-celebrating-40-years-16-july-new-york","sessions":2,"date":"2016-07-14","site":"nyc"}
{"url":"http:\/\/www.nightnyc.net\/live-music\/brand-new-modest-mouse-14-july-new-york","sessions":2,"date":"2016-07-14","site":"nyc"}
