{"url":"http:\/\/www.nightnyc.net\/live-music\/rick-faugno-sings-bobby-darin-16-january-new-york","sessions":1,"date":"2017-09-01","site":"nyc"}
{"url":"http:\/\/www.nightnyc.net\/live-music\/louisiana-philharmonic-orchestra-carlos-miguel-prieto-revueltas-glass-27-february-new-york","sessions":1,"date":"2017-09-01","site":"nyc"}
{"url":"http:\/\/www.nightnyc.net\/live-music\/erika-henningsen-30-january-new-york","sessions":1,"date":"2017-09-01","site":"nyc"}
{"url":"http:\/\/www.nightnyc.net\/live-music\/wasabassco-s-unstripped-mysteries-1-september-new-york","sessions":1,"date":"2017-09-01","site":"nyc"}
{"url":"http:\/\/www.nightnyc.net\/live-music\/zhang-fang-and-meiyan-li-piano-20-november-new-york","sessions":1,"date":"2017-09-01","site":"nyc"}
{"url":"http:\/\/www.nightnyc.net\/theatre\/jay-malsky-slept-with-my-boyfriend-obama-daughters-requiem-for-america-ucb-theatre-new-york","sessions":1,"date":"2017-09-01","site":"nyc"}
{"url":"http:\/\/www.nightnyc.net\/teatro-john-golden-theatre-septiembre-2017","sessions":1,"date":"2017-09-01","site":"nyc"}
{"url":"http:\/\/www.nightnyc.net\/party\/mile-high-fridays-no-cover-charge-and-more-on-a-c-pass-list-tkt-22-september-new-york","sessions":1,"date":"2017-09-01","site":"nyc"}
{"url":"http:\/\/www.nightnyc.net\/live-music\/boogaloo-extravaganza-30-september-new-york","sessions":1,"date":"2017-09-01","site":"nyc"}
{"url":"http:\/\/www.nightnyc.net\/live-music\/a-fine-bromance-with-jeff-kready-and-tally-sessions-7-october-new-york","sessions":1,"date":"2017-09-01","site":"nyc"}
{"url":"http:\/\/www.nightnyc.net\/live-music-flamenco-new-york","sessions":1,"date":"2017-09-01","site":"nyc"}
{"url":"http:\/\/www.nightnyc.net\/en\/highline-ballroom","sessions":1,"date":"2017-09-01","site":"nyc"}
{"url":"http:\/\/www.nightnyc.net\/live-music-new-york-april-2018","sessions":1,"date":"2017-09-01","site":"nyc"}
{"url":"http:\/\/www.nightnyc.net\/live-music-new-york-january-2018","sessions":1,"date":"2017-09-01","site":"nyc"}
{"url":"http:\/\/www.nightnyc.net\/live-music\/54-sings-ingrid-michaelson-4-september-new-york","sessions":1,"date":"2017-09-01","site":"nyc"}
{"url":"http:\/\/www.nightnyc.net\/live-music-new-york-september-2017","sessions":1,"date":"2017-09-01","site":"nyc"}
{"url":"http:\/\/www.nightnyc.net\/es\/output-club","sessions":2,"date":"2017-09-01","site":"nyc"}
{"url":"http:\/\/www.nightnyc.net\/conciertos-salsa-new-york","sessions":4,"date":"2017-09-01","site":"nyc"}
