{"url":"http:\/\/www.nightnyc.net\/party\/space-summer-night-saturdays-a-hip-hop-no-cover-rooftop-party-8-july-new-york","sessions":1,"date":"2017-07-08","site":"nyc"}
{"url":"http:\/\/www.nightnyc.net\/party\/space-summer-rooftop-saturday-party-no-cover-on-a-c-pass-list-22-july-new-york","sessions":1,"date":"2017-07-08","site":"nyc"}
{"url":"http:\/\/www.nightnyc.net\/live-music\/annette-st-john-smoke-jazz-new-york","sessions":1,"date":"2017-07-08","site":"nyc"}
{"url":"http:\/\/www.nightnyc.net\/live-music-saturday-new-york","sessions":1,"date":"2017-07-08","site":"nyc"}
{"url":"http:\/\/www.nightnyc.net\/fiestas-new-york","sessions":1,"date":"2017-07-08","site":"nyc"}
{"url":"http:\/\/www.nightnyc.net\/live-music-new-york-saturday-8-july-2017","sessions":1,"date":"2017-07-08","site":"nyc"}
{"url":"http:\/\/www.nightnyc.net\/conciertos-hip-hop-new-york","sessions":2,"date":"2017-07-08","site":"nyc"}
