{"url":"http:\/\/www.nightnyc.net\/live-music\/mat-kearney-andrew-belle-concerts-15-march-new-york","sessions":1,"date":"2017-12-05","site":"nyc"}
{"url":"http:\/\/www.nightnyc.net\/live-music\/nicky-ciampoli-as-carol-channing-14-april-new-york","sessions":1,"date":"2017-12-05","site":"nyc"}
{"url":"http:\/\/www.nightnyc.net\/live-music\/hot-97-s-hot-for-the-holidays-14-december-newark","sessions":1,"date":"2017-12-05","site":"nyc"}
{"url":"http:\/\/www.nightnyc.net\/live-music\/from-the-hit-netflix-series-narcos-capturing-pablo-an-evening-with-javier-pena-steve-murphy-2-may-red-bank","sessions":1,"date":"2017-12-05","site":"nyc"}
{"url":"http:\/\/www.nightnyc.net\/live-music\/alex-syiek-friends-hella-crazee-holidayzee-8-december-new-york","sessions":1,"date":"2017-12-05","site":"nyc"}
{"url":"http:\/\/www.nightnyc.net\/live-music\/yolanda-adams-16-december-new-york","sessions":1,"date":"2017-12-05","site":"nyc"}
{"url":"http:\/\/www.nightnyc.net\/main\/type:Fiestas.city:New York\/60","sessions":1,"date":"2017-12-05","site":"nyc"}
{"url":"http:\/\/www.nightnyc.net\/theatre\/timestalks-jodie-foster-rosemarie-dewitt-11-december-new-york","sessions":1,"date":"2017-12-05","site":"nyc"}
{"url":"http:\/\/www.nightnyc.net\/theatre\/evan-weiss-and-friends-16-december-new-york","sessions":1,"date":"2017-12-05","site":"nyc"}
{"url":"http:\/\/www.nightnyc.net\/programacion-webster-hall-diciembre-2017","sessions":1,"date":"2017-12-05","site":"nyc"}
{"url":"http:\/\/www.nightnyc.net\/obras-teatro-madison-square-garden","sessions":1,"date":"2017-12-05","site":"nyc"}
{"url":"http:\/\/www.nightnyc.net\/live-music-wednesday-new-york","sessions":1,"date":"2017-12-05","site":"nyc"}
{"url":"http:\/\/www.nightnyc.net\/live-music-new-york-sunday-8-july-2018","sessions":1,"date":"2017-12-05","site":"nyc"}
{"url":"http:\/\/www.nightnyc.net\/en\/august-wilson-theatre","sessions":1,"date":"2017-12-05","site":"nyc"}
{"url":"http:\/\/www.nightnyc.net\/en\/boulton-center","sessions":1,"date":"2017-12-05","site":"nyc"}
{"url":"http:\/\/www.nightnyc.net\/conciertos-electronica-new-york","sessions":1,"date":"2017-12-05","site":"nyc"}
{"url":"http:\/\/www.nightnyc.net\/concierto\/open-mic-monday-19-febrero-new-york","sessions":1,"date":"2017-12-05","site":"nyc"}
{"url":"http:\/\/www.nightnyc.net\/concierto\/manhattan-school-of-music-afro-cuban-jazz-orchestra-dizzy-s-new-york","sessions":1,"date":"2017-12-05","site":"nyc"}
{"url":"http:\/\/www.nightnyc.net\/en\/carnegie-hall","sessions":1,"date":"2017-12-05","site":"nyc"}
{"url":"http:\/\/www.nightnyc.net\/en\/lincoln-center","sessions":1,"date":"2017-12-05","site":"nyc"}
{"url":"http:\/\/www.nightnyc.net\/live-music-new-york-january-2018","sessions":1,"date":"2017-12-05","site":"nyc"}
{"url":"http:\/\/www.nightnyc.net\/live-music-bossa-nova-new-york","sessions":1,"date":"2017-12-05","site":"nyc"}
{"url":"http:\/\/www.nightnyc.net\/fiestas-new-york","sessions":1,"date":"2017-12-05","site":"nyc"}
{"url":"http:\/\/www.nightnyc.net\/en\/shubert-theatre","sessions":1,"date":"2017-12-05","site":"nyc"}
{"url":"http:\/\/www.nightnyc.net\/broadway-shows-new-york-december-2017","sessions":1,"date":"2017-12-05","site":"nyc"}
