{"url":"http:\/\/www.nightnyc.net\/live-music\/the-love-hangover-15-february-new-york","sessions":1,"date":"2017-02-13","site":"nyc"}
{"url":"http:\/\/www.nightnyc.net\/musica-directo-white-plains-febrero-2017","sessions":1,"date":"2017-02-13","site":"nyc"}
{"url":"http:\/\/www.nightnyc.net\/live-music\/tailgate-mixtape-country-night-nyc-valentine-s-day-14-february-new-york","sessions":1,"date":"2017-02-13","site":"nyc"}
{"url":"http:\/\/www.nightnyc.net\/live-music\/pnb-rock-14-february-new-york","sessions":1,"date":"2017-02-13","site":"nyc"}
{"url":"http:\/\/www.nightnyc.net\/live-music\/person2person-featuring-houston-person-eric-person-dizzy-s-new-york","sessions":1,"date":"2017-02-13","site":"nyc"}
{"url":"http:\/\/www.nightnyc.net\/teatro\/do-not-disturb-bam-fisher-new-york","sessions":1,"date":"2017-02-13","site":"nyc"}
{"url":"http:\/\/www.nightnyc.net\/teatro\/valentine-s-day-showcase-14-febrero-new-york","sessions":1,"date":"2017-02-13","site":"nyc"}
{"url":"http:\/\/www.nightnyc.net\/tickets-tonight-new-york","sessions":1,"date":"2017-02-13","site":"nyc"}
{"url":"http:\/\/www.nightnyc.net\/tickets-new-york-tuesday-14-february-2017","sessions":1,"date":"2017-02-13","site":"nyc"}
{"url":"http:\/\/www.nightnyc.net\/theatre\/moscow-festival-ballet-tchaikovsky-gala-2-april-new-york","sessions":1,"date":"2017-02-13","site":"nyc"}
{"url":"http:\/\/www.nightnyc.net\/theatre\/dadan-3-march-new-york","sessions":1,"date":"2017-02-13","site":"nyc"}
{"url":"http:\/\/www.nightnyc.net\/live-music\/kevin-eubanks-quartet-with-dave-holland-nicholas-payton-and-jeff-tain-watts-14-april-new-york","sessions":1,"date":"2017-02-13","site":"nyc"}
{"url":"http:\/\/www.nightnyc.net\/live-music\/jimmy-greene-39-s-love-in-action-jazz-standard-new-york","sessions":1,"date":"2017-02-13","site":"nyc"}
{"url":"http:\/\/www.nightnyc.net\/concierto\/mendelssohn-on-fire-12-febrero-new-york","sessions":1,"date":"2017-02-13","site":"nyc"}
{"url":"http:\/\/www.nightnyc.net\/concierto\/rkdn-8-marzo-new-york","sessions":1,"date":"2017-02-13","site":"nyc"}
{"url":"http:\/\/www.nightnyc.net\/concierto\/independencia-dominicana-25-febrero-new-york","sessions":1,"date":"2017-02-13","site":"nyc"}
{"url":"http:\/\/www.nightnyc.net\/concierto\/chris-bullock-s-glitch-quintet-psychaudio-intergalactic-space-allstars-dj-david-garber-2-diciembre-new-york","sessions":1,"date":"2017-02-13","site":"nyc"}
{"url":"http:\/\/www.nightnyc.net\/concerts-synth-pop-new-york","sessions":1,"date":"2017-02-13","site":"nyc"}
{"url":"http:\/\/www.nightnyc.net\/guia-conciertos-new-york-abril-2017","sessions":1,"date":"2017-02-13","site":"nyc"}
{"url":"http:\/\/www.nightnyc.net\/guia-conciertos-new-york-febrero-2017","sessions":1,"date":"2017-02-13","site":"nyc"}
{"url":"http:\/\/www.nightnyc.net\/live-music\/charito-the-john-di-martino-trio-2-march-new-york","sessions":1,"date":"2017-02-13","site":"nyc"}
{"url":"http:\/\/www.nightnyc.net\/live-music\/athena-andreadis-ready-for-the-sun-album-launch-3-february-new-york","sessions":1,"date":"2017-02-13","site":"nyc"}
{"url":"http:\/\/www.nightnyc.net\/live-music-saturday-new-york","sessions":1,"date":"2017-02-13","site":"nyc"}
{"url":"http:\/\/www.nightnyc.net\/guia-conciertos-underground-new-york","sessions":1,"date":"2017-02-13","site":"nyc"}
{"url":"http:\/\/www.nightnyc.net\/theatre\/my-funny-valentine-14-february-new-york","sessions":2,"date":"2017-02-13","site":"nyc"}
